vkit_doc_tool/__init__.py
vkit_doc_tool-0.1.0.dist-info/LICENSE
vkit_doc_tool-0.1.0.dist-info/METADATA
vkit_doc_tool-0.1.0.dist-info/WHEEL
vkit_doc_tool-0.1.0.dist-info/entry_points.txt
vkit_doc_tool-0.1.0.dist-info/top_level.txt
vkit_doc_tool-0.1.0.dist-info/RECORD
