Metadata-Version: 2.1
Name: vkit-doc-tool
Version: 0.1.0
Summary: todo
Home-page: https://github.com/huntzhan/vkit-doc-tool
Author: Hunt Zhan
Author-email: huntzhan.dev@gmail.com
License: Apache-2.0
Platform: UNKNOWN
Requires-Python: ~=3.8
License-File: LICENSE
Requires-Dist: toml
Requires-Dist: attrs
Requires-Dist: cattrs
Requires-Dist: iolite
Requires-Dist: markdown-toc
Requires-Dist: fire
Provides-Extra: dev
Requires-Dist: build (>=0.2.1) ; extra == 'dev'
Requires-Dist: fireball (>=0.5.0) ; extra == 'dev'
Requires-Dist: iolite (>=0.3.0) ; extra == 'dev'
Requires-Dist: pytest (>=6.1.2) ; extra == 'dev'
Requires-Dist: yapf (>=0.30.0) ; extra == 'dev'
Requires-Dist: flake8 (>=3.8.4) ; extra == 'dev'
Requires-Dist: pdoc3 (>=0.9.2) ; extra == 'dev'
Requires-Dist: twine (>=3.2.0) ; extra == 'dev'
Requires-Dist: ipython (>=7.20.0) ; extra == 'dev'
Requires-Dist: pdbpp (>=0.10.2) ; extra == 'dev'
Requires-Dist: rope (>=0.18.0) ; extra == 'dev'
